{
  "name": "gh-skills-builder",
  "description": "Design, build, review, and publish GitHub Skills-style exercises with custom agents and Agent Skills for learner journeys, workflow-backed validation, and release readiness.",
  "version": "1.0.2",
  "keywords": [
    "github-skills",
    "education",
    "curriculum",
    "exercise-creation",
    "custom-agents",
    "agent-skills"
  ],
  "author": {
    "name": "Ari LiVigni"
  },
  "repository": "https://github.com/arilivigni/gh-skills-builder",
  "license": "MIT",
  "agents": [
    "./agents"
  ],
  "skills": [
    "./skills/create-github-skills-outline",
    "./skills/bootstrap-github-skills-exercise",
    "./skills/review-github-skills-exercise",
    "./skills/publish-github-skills-exercise"
  ]
}
